[
  {
    "date": "2026-03-16",
    "model_id": "A",
    "bybit_equity_usd": "10021.496021",
    "bybit_total_pnl_usd": "21.496021",
    "bybit_realized_pnl_usd": "0.0",
    "bybit_unrealized_pnl_usd": "21.496021",
    "bybit_win_rate": "0.0",
    "bybit_closed_trades": "0",
    "total_equity_usd": "20021.496021",
    "total_pnl_usd": "21.496021",
    "realized_pnl_usd": "0.0",
    "unrealized_pnl_usd": "21.496021",
    "win_rate": "0.0",
    "closed_trades": "0"
  },
  {
    "date": "2026-03-16",
    "model_id": "B",
    "bybit_equity_usd": "11575.890703",
    "bybit_total_pnl_usd": "1575.890703",
    "bybit_realized_pnl_usd": "0.0",
    "bybit_unrealized_pnl_usd": "1575.890703",
    "bybit_win_rate": "0.0",
    "bybit_closed_trades": "0",
    "total_equity_usd": "21575.890703",
    "total_pnl_usd": "1575.890703",
    "realized_pnl_usd": "0.0",
    "unrealized_pnl_usd": "1575.890703",
    "win_rate": "0.0",
    "closed_trades": "0"
  },
  {
    "date": "2026-03-16",
    "model_id": "C",
    "bybit_equity_usd": "21455.769907",
    "bybit_total_pnl_usd": "11455.769907",
    "bybit_realized_pnl_usd": "7645.164583",
    "bybit_unrealized_pnl_usd": "3810.605324",
    "bybit_win_rate": "72.7273",
    "bybit_closed_trades": "11",
    "total_equity_usd": "31455.769907",
    "total_pnl_usd": "11455.769907",
    "realized_pnl_usd": "7645.164583",
    "unrealized_pnl_usd": "3810.605324",
    "win_rate": "72.7273",
    "closed_trades": "11"
  },
  {
    "date": "2026-03-16",
    "model_id": "D",
    "bybit_equity_usd": "8266.896178",
    "bybit_total_pnl_usd": "-1733.103822",
    "bybit_realized_pnl_usd": "-1884.755317",
    "bybit_unrealized_pnl_usd": "151.651494",
    "bybit_win_rate": "0.0",
    "bybit_closed_trades": "11",
    "total_equity_usd": "8266.896178",
    "total_pnl_usd": "-11733.103822",
    "realized_pnl_usd": "-1884.755317",
    "unrealized_pnl_usd": "151.651494",
    "win_rate": "0.0",
    "closed_trades": "11"
  },
  {
    "date": "2026-03-17",
    "model_id": "A",
    "bybit_equity_usd": "10287.868999",
    "bybit_total_pnl_usd": "287.868999",
    "bybit_realized_pnl_usd": "264.067692",
    "bybit_unrealized_pnl_usd": "23.801307",
    "bybit_win_rate": "44.8276",
    "bybit_closed_trades": "29",
    "total_equity_usd": "20287.868999",
    "total_pnl_usd": "287.868999",
    "realized_pnl_usd": "264.067692",
    "unrealized_pnl_usd": "23.801307",
    "win_rate": "44.8276",
    "closed_trades": "29"
  },
  {
    "date": "2026-03-17",
    "model_id": "B",
    "bybit_equity_usd": "10717.613577",
    "bybit_total_pnl_usd": "717.613577",
    "bybit_realized_pnl_usd": "0.0",
    "bybit_unrealized_pnl_usd": "717.613577",
    "bybit_win_rate": "0.0",
    "bybit_closed_trades": "0",
    "total_equity_usd": "20717.613577",
    "total_pnl_usd": "717.613577",
    "realized_pnl_usd": "0.0",
    "unrealized_pnl_usd": "717.613577",
    "win_rate": "0.0",
    "closed_trades": "0"
  },
  {
    "date": "2026-03-17",
    "model_id": "C",
    "bybit_equity_usd": "17487.557448",
    "bybit_total_pnl_usd": "7487.557448",
    "bybit_realized_pnl_usd": "5926.569296",
    "bybit_unrealized_pnl_usd": "1560.988153",
    "bybit_win_rate": "47.8261",
    "bybit_closed_trades": "23",
    "total_equity_usd": "27487.557448",
    "total_pnl_usd": "7487.557448",
    "realized_pnl_usd": "5926.569296",
    "unrealized_pnl_usd": "1560.988153",
    "win_rate": "47.8261",
    "closed_trades": "23"
  },
  {
    "date": "2026-03-17",
    "model_id": "D",
    "bybit_equity_usd": "8786.823132",
    "bybit_total_pnl_usd": "-1213.176868",
    "bybit_realized_pnl_usd": "-1570.42041",
    "bybit_unrealized_pnl_usd": "357.243541",
    "bybit_win_rate": "31.3725",
    "bybit_closed_trades": "51",
    "total_equity_usd": "8786.823132",
    "total_pnl_usd": "-11213.176868",
    "realized_pnl_usd": "-1570.42041",
    "unrealized_pnl_usd": "357.243541",
    "win_rate": "31.3725",
    "closed_trades": "51"
  },
  {
    "date": "2026-03-18",
    "model_id": "A",
    "bybit_equity_usd": "9031.898633",
    "bybit_total_pnl_usd": "-968.101367",
    "bybit_realized_pnl_usd": "-968.101367",
    "bybit_unrealized_pnl_usd": "0.0",
    "bybit_win_rate": "23.4375",
    "bybit_closed_trades": "64",
    "total_equity_usd": "19031.898633",
    "total_pnl_usd": "-968.101367",
    "realized_pnl_usd": "-968.101367",
    "unrealized_pnl_usd": "0.0",
    "win_rate": "23.4375",
    "closed_trades": "64"
  },
  {
    "date": "2026-03-18",
    "model_id": "B",
    "bybit_equity_usd": "8578.137902",
    "bybit_total_pnl_usd": "-1421.862098",
    "bybit_realized_pnl_usd": "-1421.862098",
    "bybit_unrealized_pnl_usd": "0.0",
    "bybit_win_rate": "0.0",
    "bybit_closed_trades": "3",
    "total_equity_usd": "18578.137902",
    "total_pnl_usd": "-1421.862098",
    "realized_pnl_usd": "-1421.862098",
    "unrealized_pnl_usd": "0.0",
    "win_rate": "0.0",
    "closed_trades": "3"
  },
  {
    "date": "2026-03-18",
    "model_id": "C",
    "bybit_equity_usd": "16643.98016",
    "bybit_total_pnl_usd": "6643.98016",
    "bybit_realized_pnl_usd": "6643.98016",
    "bybit_unrealized_pnl_usd": "0.0",
    "bybit_win_rate": "38.2353",
    "bybit_closed_trades": "34",
    "total_equity_usd": "26643.98016",
    "total_pnl_usd": "6643.98016",
    "realized_pnl_usd": "6643.98016",
    "unrealized_pnl_usd": "0.0",
    "win_rate": "38.2353",
    "closed_trades": "34"
  },
  {
    "date": "2026-03-18",
    "model_id": "D",
    "bybit_equity_usd": "10056.995256",
    "bybit_total_pnl_usd": "56.995256",
    "bybit_realized_pnl_usd": "56.995256",
    "bybit_unrealized_pnl_usd": "0.0",
    "bybit_win_rate": "41.1765",
    "bybit_closed_trades": "68",
    "total_equity_usd": "10056.995256",
    "total_pnl_usd": "-9943.004744",
    "realized_pnl_usd": "56.995256",
    "unrealized_pnl_usd": "0.0",
    "win_rate": "41.1765",
    "closed_trades": "68"
  },
  {
    "date": "2026-03-19",
    "model_id": "A",
    "bybit_equity_usd": "9251.805731",
    "bybit_total_pnl_usd": "-748.194269",
    "bybit_realized_pnl_usd": "-1214.231627",
    "bybit_unrealized_pnl_usd": "466.037358",
    "bybit_win_rate": "0.0",
    "bybit_closed_trades": "21",
    "total_equity_usd": "19251.805731",
    "total_pnl_usd": "-748.194269",
    "realized_pnl_usd": "-1214.231627",
    "unrealized_pnl_usd": "466.037358",
    "win_rate": "0.0",
    "closed_trades": "21"
  },
  {
    "date": "2026-03-19",
    "model_id": "B",
    "bybit_equity_usd": "7904.7791",
    "bybit_total_pnl_usd": "-2095.2209",
    "bybit_realized_pnl_usd": "-2095.2209",
    "bybit_unrealized_pnl_usd": "0.0",
    "bybit_win_rate": "0.0",
    "bybit_closed_trades": "5",
    "total_equity_usd": "17904.7791",
    "total_pnl_usd": "-2095.2209",
    "realized_pnl_usd": "-2095.2209",
    "unrealized_pnl_usd": "0.0",
    "win_rate": "0.0",
    "closed_trades": "5"
  },
  {
    "date": "2026-03-19",
    "model_id": "C",
    "bybit_equity_usd": "11240.578261",
    "bybit_total_pnl_usd": "1240.578261",
    "bybit_realized_pnl_usd": "0.0",
    "bybit_unrealized_pnl_usd": "1240.578261",
    "bybit_win_rate": "0.0",
    "bybit_closed_trades": "0",
    "total_equity_usd": "21240.578261",
    "total_pnl_usd": "1240.578261",
    "realized_pnl_usd": "0.0",
    "unrealized_pnl_usd": "1240.578261",
    "win_rate": "0.0",
    "closed_trades": "0"
  },
  {
    "date": "2026-03-19",
    "model_id": "D",
    "bybit_equity_usd": "12515.609184",
    "bybit_total_pnl_usd": "2515.609184",
    "bybit_realized_pnl_usd": "2515.609184",
    "bybit_unrealized_pnl_usd": "0.0",
    "bybit_win_rate": "50.0",
    "bybit_closed_trades": "12",
    "total_equity_usd": "12515.609184",
    "total_pnl_usd": "-7484.390816",
    "realized_pnl_usd": "2515.609184",
    "unrealized_pnl_usd": "0.0",
    "win_rate": "50.0",
    "closed_trades": "12"
  },
  {
    "date": "2026-03-20",
    "model_id": "A",
    "bybit_equity_usd": "9577.076681",
    "bybit_total_pnl_usd": "-422.923319",
    "bybit_realized_pnl_usd": "-581.03614",
    "bybit_unrealized_pnl_usd": "158.11282",
    "bybit_win_rate": "21.7391",
    "bybit_closed_trades": "23",
    "total_equity_usd": "19577.076681",
    "total_pnl_usd": "-422.923319",
    "realized_pnl_usd": "-581.03614",
    "unrealized_pnl_usd": "158.11282",
    "win_rate": "21.7391",
    "closed_trades": "23"
  },
  {
    "date": "2026-03-20",
    "model_id": "B",
    "bybit_equity_usd": "11561.287857",
    "bybit_total_pnl_usd": "1561.287857",
    "bybit_realized_pnl_usd": "1006.991673",
    "bybit_unrealized_pnl_usd": "554.296184",
    "bybit_win_rate": "42.8571",
    "bybit_closed_trades": "21",
    "total_equity_usd": "21561.287857",
    "total_pnl_usd": "1561.287857",
    "realized_pnl_usd": "1006.991673",
    "unrealized_pnl_usd": "554.296184",
    "win_rate": "42.8571",
    "closed_trades": "21"
  },
  {
    "date": "2026-03-20",
    "model_id": "C",
    "bybit_equity_usd": "9533.36729",
    "bybit_total_pnl_usd": "-466.63271",
    "bybit_realized_pnl_usd": "-1522.049359",
    "bybit_unrealized_pnl_usd": "1055.41665",
    "bybit_win_rate": "0.0",
    "bybit_closed_trades": "6",
    "total_equity_usd": "19533.36729",
    "total_pnl_usd": "-466.63271",
    "realized_pnl_usd": "-1522.049359",
    "unrealized_pnl_usd": "1055.41665",
    "win_rate": "0.0",
    "closed_trades": "6"
  },
  {
    "date": "2026-03-20",
    "model_id": "D",
    "bybit_equity_usd": "9902.499724",
    "bybit_total_pnl_usd": "-97.500276",
    "bybit_realized_pnl_usd": "-157.359634",
    "bybit_unrealized_pnl_usd": "59.859358",
    "bybit_win_rate": "34.6154",
    "bybit_closed_trades": "26",
    "total_equity_usd": "9902.499724",
    "total_pnl_usd": "-10097.500276",
    "realized_pnl_usd": "-157.359634",
    "unrealized_pnl_usd": "59.859358",
    "win_rate": "34.6154",
    "closed_trades": "26"
  },
  {
    "date": "2026-03-21",
    "model_id": "A",
    "bybit_equity_usd": "10688.566984",
    "bybit_total_pnl_usd": "688.566984",
    "bybit_realized_pnl_usd": "678.429215",
    "bybit_unrealized_pnl_usd": "10.13777",
    "bybit_win_rate": "30.9524",
    "bybit_closed_trades": "42",
    "total_equity_usd": "20688.566984",
    "total_pnl_usd": "688.566984",
    "realized_pnl_usd": "678.429215",
    "unrealized_pnl_usd": "10.13777",
    "win_rate": "30.9524",
    "closed_trades": "42"
  },
  {
    "date": "2026-03-21",
    "model_id": "B",
    "bybit_equity_usd": "10864.84759",
    "bybit_total_pnl_usd": "864.84759",
    "bybit_realized_pnl_usd": "847.290334",
    "bybit_unrealized_pnl_usd": "17.557256",
    "bybit_win_rate": "41.4634",
    "bybit_closed_trades": "41",
    "total_equity_usd": "20864.84759",
    "total_pnl_usd": "864.84759",
    "realized_pnl_usd": "847.290334",
    "unrealized_pnl_usd": "17.557256",
    "win_rate": "41.4634",
    "closed_trades": "41"
  },
  {
    "date": "2026-03-21",
    "model_id": "C",
    "bybit_equity_usd": "6815.85749",
    "bybit_total_pnl_usd": "-3184.14251",
    "bybit_realized_pnl_usd": "-3421.306647",
    "bybit_unrealized_pnl_usd": "237.164137",
    "bybit_win_rate": "16.6667",
    "bybit_closed_trades": "18",
    "total_equity_usd": "16815.85749",
    "total_pnl_usd": "-3184.14251",
    "realized_pnl_usd": "-3421.306647",
    "unrealized_pnl_usd": "237.164137",
    "win_rate": "16.6667",
    "closed_trades": "18"
  },
  {
    "date": "2026-03-21",
    "model_id": "D",
    "bybit_equity_usd": "11404.600493",
    "bybit_total_pnl_usd": "1404.600493",
    "bybit_realized_pnl_usd": "1349.917539",
    "bybit_unrealized_pnl_usd": "54.682955",
    "bybit_win_rate": "40.3226",
    "bybit_closed_trades": "62",
    "total_equity_usd": "11404.600493",
    "total_pnl_usd": "-8595.399507",
    "realized_pnl_usd": "1349.917539",
    "unrealized_pnl_usd": "54.682955",
    "win_rate": "40.3226",
    "closed_trades": "62"
  },
  {
    "date": "2026-03-22",
    "model_id": "A",
    "bybit_equity_usd": 9646.524348,
    "bybit_total_pnl_usd": -353.475652,
    "bybit_realized_pnl_usd": -495.78239,
    "bybit_unrealized_pnl_usd": 142.306738,
    "bybit_win_rate": 10.0,
    "bybit_closed_trades": 30,
    "total_equity_usd": 19646.524348,
    "total_pnl_usd": -353.475652,
    "realized_pnl_usd": -495.78239,
    "unrealized_pnl_usd": 142.306738,
    "win_rate": 10.0,
    "closed_trades": 30
  },
  {
    "date": "2026-03-22",
    "model_id": "B",
    "bybit_equity_usd": 10195.625389,
    "bybit_total_pnl_usd": 195.625389,
    "bybit_realized_pnl_usd": -128.170669,
    "bybit_unrealized_pnl_usd": 323.796058,
    "bybit_win_rate": 25.0,
    "bybit_closed_trades": 8,
    "total_equity_usd": 20195.625389,
    "total_pnl_usd": 195.625389,
    "realized_pnl_usd": -128.170669,
    "unrealized_pnl_usd": 323.796058,
    "win_rate": 25.0,
    "closed_trades": 8
  },
  {
    "date": "2026-03-22",
    "model_id": "C",
    "bybit_equity_usd": 10068.957113,
    "bybit_total_pnl_usd": 68.957113,
    "bybit_realized_pnl_usd": -994.808843,
    "bybit_unrealized_pnl_usd": 1063.765956,
    "bybit_win_rate": 0.0,
    "bybit_closed_trades": 1,
    "total_equity_usd": 20068.957113,
    "total_pnl_usd": 68.957113,
    "realized_pnl_usd": -994.808843,
    "unrealized_pnl_usd": 1063.765956,
    "win_rate": 0.0,
    "closed_trades": 1
  },
  {
    "date": "2026-03-22",
    "model_id": "D",
    "bybit_equity_usd": 9673.24565,
    "bybit_total_pnl_usd": -326.75435,
    "bybit_realized_pnl_usd": -311.321062,
    "bybit_unrealized_pnl_usd": -15.433288,
    "bybit_win_rate": 23.0769,
    "bybit_closed_trades": 13,
    "total_equity_usd": 9673.24565,
    "total_pnl_usd": -10326.75435,
    "realized_pnl_usd": -311.321062,
    "unrealized_pnl_usd": -15.433288,
    "win_rate": 23.0769,
    "closed_trades": 13
  }
]