[
  {
    "date": "2026-03-16",
    "model_id": "A",
    "bybit_equity_usd": "10021.496021",
    "bybit_total_pnl_usd": "21.496021",
    "bybit_realized_pnl_usd": "0.0",
    "bybit_unrealized_pnl_usd": "21.496021",
    "bybit_win_rate": "0.0",
    "bybit_closed_trades": "0",
    "total_equity_usd": "20021.496021",
    "total_pnl_usd": "21.496021",
    "realized_pnl_usd": "0.0",
    "unrealized_pnl_usd": "21.496021",
    "win_rate": "0.0",
    "closed_trades": "0"
  },
  {
    "date": "2026-03-16",
    "model_id": "B",
    "bybit_equity_usd": "11575.890703",
    "bybit_total_pnl_usd": "1575.890703",
    "bybit_realized_pnl_usd": "0.0",
    "bybit_unrealized_pnl_usd": "1575.890703",
    "bybit_win_rate": "0.0",
    "bybit_closed_trades": "0",
    "total_equity_usd": "21575.890703",
    "total_pnl_usd": "1575.890703",
    "realized_pnl_usd": "0.0",
    "unrealized_pnl_usd": "1575.890703",
    "win_rate": "0.0",
    "closed_trades": "0"
  },
  {
    "date": "2026-03-16",
    "model_id": "C",
    "bybit_equity_usd": "21455.769907",
    "bybit_total_pnl_usd": "11455.769907",
    "bybit_realized_pnl_usd": "7645.164583",
    "bybit_unrealized_pnl_usd": "3810.605324",
    "bybit_win_rate": "72.7273",
    "bybit_closed_trades": "11",
    "total_equity_usd": "31455.769907",
    "total_pnl_usd": "11455.769907",
    "realized_pnl_usd": "7645.164583",
    "unrealized_pnl_usd": "3810.605324",
    "win_rate": "72.7273",
    "closed_trades": "11"
  },
  {
    "date": "2026-03-16",
    "model_id": "D",
    "bybit_equity_usd": "8266.896178",
    "bybit_total_pnl_usd": "-1733.103822",
    "bybit_realized_pnl_usd": "-1884.755317",
    "bybit_unrealized_pnl_usd": "151.651494",
    "bybit_win_rate": "0.0",
    "bybit_closed_trades": "11",
    "total_equity_usd": "8266.896178",
    "total_pnl_usd": "-11733.103822",
    "realized_pnl_usd": "-1884.755317",
    "unrealized_pnl_usd": "151.651494",
    "win_rate": "0.0",
    "closed_trades": "11"
  },
  {
    "date": "2026-03-17",
    "model_id": "A",
    "bybit_equity_usd": 10287.868999,
    "bybit_total_pnl_usd": 287.868999,
    "bybit_realized_pnl_usd": 264.067692,
    "bybit_unrealized_pnl_usd": 23.801307,
    "bybit_win_rate": 44.8276,
    "bybit_closed_trades": 29,
    "total_equity_usd": 20287.868999,
    "total_pnl_usd": 287.868999,
    "realized_pnl_usd": 264.067692,
    "unrealized_pnl_usd": 23.801307,
    "win_rate": 44.8276,
    "closed_trades": 29
  },
  {
    "date": "2026-03-17",
    "model_id": "B",
    "bybit_equity_usd": 10717.613577,
    "bybit_total_pnl_usd": 717.613577,
    "bybit_realized_pnl_usd": 0.0,
    "bybit_unrealized_pnl_usd": 717.613577,
    "bybit_win_rate": 0.0,
    "bybit_closed_trades": 0,
    "total_equity_usd": 20717.613577,
    "total_pnl_usd": 717.613577,
    "realized_pnl_usd": 0.0,
    "unrealized_pnl_usd": 717.613577,
    "win_rate": 0.0,
    "closed_trades": 0
  },
  {
    "date": "2026-03-17",
    "model_id": "C",
    "bybit_equity_usd": 17487.557448,
    "bybit_total_pnl_usd": 7487.557448,
    "bybit_realized_pnl_usd": 5926.569296,
    "bybit_unrealized_pnl_usd": 1560.988153,
    "bybit_win_rate": 47.8261,
    "bybit_closed_trades": 23,
    "total_equity_usd": 27487.557448,
    "total_pnl_usd": 7487.557448,
    "realized_pnl_usd": 5926.569296,
    "unrealized_pnl_usd": 1560.988153,
    "win_rate": 47.8261,
    "closed_trades": 23
  },
  {
    "date": "2026-03-17",
    "model_id": "D",
    "bybit_equity_usd": 8786.823132,
    "bybit_total_pnl_usd": -1213.176868,
    "bybit_realized_pnl_usd": -1570.42041,
    "bybit_unrealized_pnl_usd": 357.243541,
    "bybit_win_rate": 31.3725,
    "bybit_closed_trades": 51,
    "total_equity_usd": 8786.823132,
    "total_pnl_usd": -11213.176868,
    "realized_pnl_usd": -1570.42041,
    "unrealized_pnl_usd": 357.243541,
    "win_rate": 31.3725,
    "closed_trades": 51
  }
]